{"short_definition":"A bankruptcy case filed to reduce or eliminate debts that are primarily consumer debts.","long_definition_html":"<p>A bankruptcy case filed to reduce or eliminate debts that are primarily consumer debts. </p>","long_definition_markdown":"A bankruptcy case filed to reduce or eliminate debts that are primarily consumer debts. ","long_definition_text":"A bankruptcy case filed to reduce or eliminate debts that are primarily consumer debts.","source":"US Courts Glossary","source_url":"http://www.uscourts.gov/Common/Glossary.aspx"}